{"kind": "customsearch#result", "title": "Llantrisant", "displayLink": "www.facebook.com", "htmlTitle": "Llantrisant", "formattedUrl": "https://www.facebook.com/Llantrisant-351197722385/", "htmlFormattedUrl": "https://www.facebook.com/Llantrisant-351197722385/", "pagemap": {"metatags": [{"al:ios:url": "fb://page/?id=351197722385", "al:ios:app_store_id": "284882215", "referrer": "default", "al:android:package": "com.facebook.katana", "al:ios:app_name": "Facebook", "al:android:url": "fb://page/351197722385", "al:android:app_name": "Facebook"}], "organization": [{"name": "Llantrisant"}], "postaladdress": [{"postalcode": "CF728SP", "streetaddress": "Castle Green"}]}, "snippet": "Llantrisant. 2435 likes \u00b7 160 talking about this. A celebration of a wonderfully \nhistoric Welsh hilltop town that people love to visit and residents are...", "htmlSnippet": "Llantrisant. 2435 likes \u00b7 160 talking about this. A celebration of a wonderfully <br>\nhistoric Welsh hilltop town that people love to visit and residents are...", "link": "https://www.facebook.com/Llantrisant-351197722385/", "time": "2016-01-18 00:00", "cacheId": "WpossyeaGlIJ"}
