{"kind": "customsearch#result", "title": "Methow Valley News", "displayLink": "www.facebook.com", "htmlTitle": "Methow Valley News", "formattedUrl": "https://www.facebook.com/pages/Methow.../128607483863863", "htmlFormattedUrl": "https://www.facebook.com/pages/Methow.../128607483863863", "pagemap": {"metatags": [{"al:ios:url": "fb://page/?id=128607483863863", "al:ios:app_store_id": "284882215", "referrer": "default", "al:android:package": "com.facebook.katana", "al:ios:app_name": "Facebook", "al:android:url": "fb://page/128607483863863", "al:android:app_name": "Facebook"}], "organization": [{"name": "Methow Valley News"}]}, "snippet": "There was a wedding set found in Winthrop at the grocery store outsi...de in the \nparking lot if someone is missing one . go in and give them the details. See More.", "htmlSnippet": "There was a wedding set found in Winthrop at the grocery store outsi...de in the <br>\nparking lot if someone is missing one . go in and give them the details. See More.", "link": "https://www.facebook.com/pages/Methow-Valley-News/128607483863863", "time": "2016-01-04 14:00", "cacheId": "SGh0T8eBACMJ"}
