{"kind": "customsearch#result", "title": "thebigtino", "displayLink": "www.facebook.com", "htmlTitle": "thebigtino", "formattedUrl": "https://www.facebook.com/thebigtino?ref=stream", "htmlFormattedUrl": "https://www.facebook.com/thebigtino?ref=stream", "pagemap": {"metatags": [{"al:ios:url": "fb://page/?id=218195361024", "al:ios:app_store_id": "284882215", "referrer": "default", "al:android:package": "com.facebook.katana", "al:ios:app_name": "Facebook", "al:android:url": "fb://page/218195361024", "al:android:app_name": "Facebook"}], "organization": [{"name": "thebigtino"}]}, "snippet": "thebigtino. 879029 likes \u00b7 39907 talking about this. http://thebigtino.com Latino. \nPop. Culture. On Instagram: http://instagram.com/thebigtino On...", "htmlSnippet": "thebigtino. 879029 likes \u00b7 39907 talking about this. http://thebigtino.com Latino. <br>\nPop. Culture. On Instagram: http://instagram.com/thebigtino On...", "link": "https://www.facebook.com/thebigtino?ref=stream", "time": "2016-01-11 23:00", "cacheId": "2gOG-PM3Hd8J"}
