{"kind": "customsearch#result", "title": "Servpro of Coos Curry and Del Norte Counties", "displayLink": "www.facebook.com", "htmlTitle": "Servpro of Coos Curry and Del Norte Counties", "formattedUrl": "https://www.facebook.com/Servpro-of-Coos-Curry-and-Del-Norte-Counties- 469428426459430/", "htmlFormattedUrl": "https://www.facebook.com/Servpro-of-Coos-Curry-and-Del-Norte-Counties- 469428426459430/", "pagemap": {"metatags": [{"al:ios:url": "fb://page/?id=469428426459430", "al:ios:app_store_id": "284882215", "referrer": "default", "al:android:package": "com.facebook.katana", "al:ios:app_name": "Facebook", "al:android:url": "fb://page/469428426459430", "al:android:app_name": "Facebook"}], "aggregaterating": [{"ratingvalue": "5", "ratingcount": "6"}], "postaladdress": [{"addresslocality": "North Bend, Oregon", "postalcode": "97459", "streetaddress": "1640 Maple St, Ste B"}], "localbusiness": [{"name": "Servpro of Coos Curry and Del Norte Counties"}], "hreviewaggregate": [{"votes": "6"}]}, "snippet": "Heavy rainfall was \"obviously\" part of the landslide that smashed Highway 42, an \nODOT official says, but \"certainly we believe some of the slide movement was\u00a0...", "htmlSnippet": "Heavy rainfall was &quot;obviously&quot; part of the <b>landslide</b> that smashed Highway 42, an <br>\nODOT official says, but &quot;certainly we believe some of the slide movement was&nbsp;...", "link": "https://www.facebook.com/Servpro-of-Coos-Curry-and-Del-Norte-Counties-469428426459430/", "time": "2016-01-10 01:00", "cacheId": "m_-BhboRWDMJ"}
{"kind": "customsearch#result", "title": "5NEWS", "displayLink": "www.facebook.com", "htmlTitle": "5NEWS", "formattedUrl": "https://www.facebook.com/5news", "htmlFormattedUrl": "https://www.facebook.com/5news", "pagemap": {"metatags": [{"al:ios:url": "fb://page/?id=136278800719", "al:ios:app_store_id": "284882215", "referrer": "default", "al:android:package": "com.facebook.katana", "al:ios:app_name": "Facebook", "al:android:url": "fb://page/136278800719", "al:android:app_name": "Facebook"}], "organization": [{"name": "5NEWS"}]}, "snippet": "5NEWS. 145105 likes \u00b7 51971 talking about this. Have a story idea? Email us \nnews@kfsm.com.", "htmlSnippet": "5NEWS. 145105 likes \u00b7 51971 talking about this. Have a story idea? Email us <br>\nnews@kfsm.com.", "link": "https://www.facebook.com/5news", "time": "2016-01-10 01:00", "cacheId": "aqdx1zsxdfkJ"}
